{
  "author": "wondible",
  "build": "94684",
  "category": ["gw", "cheat", "titans"],
  "context": "client",
  "date": "2016/07/12",
  "description": "Permanently unlocks all loadouts in Galactic War. You may remove the mod once unlocked.",
  "display_name": "Unlock Loadouts for galactic war",
  "forum": "https://forums.uberent.com/threads/rel-gw-unlock-loadouts.71320/",
  "icon": "http://wondible.com/pa/icons/gw_unlock_loadouts.png",
  "identifier": "com.wondible.pa.gw_unlock_loadouts",
  "priority": 100,
  "scenes": {
    "start": [
      "coui://ui/mods/gw_unlock_loadouts/start.js",
      "coui://ui/mods/gw_unlock_loadouts/gwo.js"
    ]
  },
  "signature": "not yet implemented",
  "version": "1.0.2"
}
